xronos_dashboard/__init__.py
xronos_dashboard/__main__.py
xronos_dashboard/py.typed
xronos_dashboard/resources/docker-compose.yml.jinja2
xronos_dashboard/resources/grafana/datasources/datasources.yml.jinja2
xronos_dashboard/resources/otel_collector/config.yml.jinja2
xronos_dashboard-0.8.0.dist-info/METADATA
xronos_dashboard-0.8.0.dist-info/WHEEL
xronos_dashboard-0.8.0.dist-info/entry_points.txt
xronos_dashboard-0.8.0.dist-info/RECORD
