Metadata-Version: 2.4
Name: xronos-dashboard
Version: 0.8.0
Summary: Dashboard for xronos programs
Project-URL: Homepage, https://xronos.com
Project-URL: Documentation, https://xronos-inc.github.io/xronos/index.html
Author-email: Christian Menard <christian@xronos.com>, Peter Donovan <peter@xronos.com>
Maintainer-email: Christian Menard <christian@xronos.com>
License-Expression: LicenseRef-Xronos-Commercial-License-v1
Classifier: Development Status :: 3 - Alpha
Classifier: Intended Audience :: Developers
Classifier: Programming Language :: Python :: 3
Classifier: Programming Language :: Python :: 3.10
Classifier: Programming Language :: Python :: 3.11
Classifier: Programming Language :: Python :: 3.12
Classifier: Programming Language :: Python :: 3.13
Classifier: Programming Language :: Python :: 3.14
Classifier: Topic :: Scientific/Engineering
Classifier: Topic :: Software Development :: Embedded Systems
Requires-Python: >=3.10
Requires-Dist: click
Requires-Dist: halo
Requires-Dist: jinja2<4.0.0,>=3.0.0
Requires-Dist: platformdirs<5.0.0,>=4.0.0
